<?xml version='1.0' encoding='UTF-8'?><magicdraw><extensionend id="8870a4ef-c381-4477-9dfe-1166f30ded25" refElementId="8870a4ef-c381-4477-9dfe-1166f30ded25" humanType="Extension End" classType="ExtensionEnd" requireSort="node" icon="index_files/icon_extensionend_1327170644.jpg"><visibility humanName="Visibility">private</visibility><upperValue refid="1f280aff-0415-4045-b157-bb340b67dc58" refElementId="1f280aff-0415-4045-b157-bb340b67dc58" humanType="Literal Unlimited Natural" classType="LiteralUnlimitedNatural" name="1" text="1" icon="index_files/icon_literalunlimitednatural_1543615404.jpg" humanName="Upper Value"/><upper humanName="Upper">1</upper><type refid="c70f2acb-e626-471d-bdc2-eafa8a91de5a" refElementId="c70f2acb-e626-471d-bdc2-eafa8a91de5a" humanType="Stereotype" classType="Stereotype" name="SentinelScenario" icon="index_files/icon_stereotype_676578603.jpg" humanName="Type"/><redefinitionContext humanName="Redefinition Context"><extension refid="addc852d-1847-4841-b9bd-0c6aacdf57ef" refElementId="addc852d-1847-4841-b9bd-0c6aacdf57ef" humanType="Extension" classType="Extension" name="Extension[extension_Sentinel Scenario:SentinelScenario - base_Activity:Activity]" isRelationship="true" icon="index_files/icon_extension_1763508892.jpg"/></redefinitionContext><qualifiedName humanName="Qualified Name">Sentinel Profile::::extension_Sentinel Scenario</qualifiedName><owningAssociation refid="addc852d-1847-4841-b9bd-0c6aacdf57ef" refElementId="addc852d-1847-4841-b9bd-0c6aacdf57ef" humanType="Extension" classType="Extension" name="Extension[extension_Sentinel Scenario:SentinelScenario - base_Activity:Activity]" isRelationship="true" icon="index_files/icon_extension_1763508892.jpg" humanName="Owning Association"/><owner refid="addc852d-1847-4841-b9bd-0c6aacdf57ef" refElementId="addc852d-1847-4841-b9bd-0c6aacdf57ef" humanType="Extension" classType="Extension" name="Extension[extension_Sentinel Scenario:SentinelScenario - base_Activity:Activity]" isRelationship="true" icon="index_files/icon_extension_1763508892.jpg" humanName="Owner"/><ownedElement humanName="Owned Element"><literalinteger refid="25a8354b-e241-4cf6-981d-62b159934ef4" refElementId="25a8354b-e241-4cf6-981d-62b159934ef4" humanType="Literal Integer" classType="LiteralInteger" name="0" text="0" icon="index_files/icon_literalinteger_602632507.jpg"/><literalunlimitednatural refid="1f280aff-0415-4045-b157-bb340b67dc58" refElementId="1f280aff-0415-4045-b157-bb340b67dc58" humanType="Literal Unlimited Natural" classType="LiteralUnlimitedNatural" name="1" text="1" icon="index_files/icon_literalunlimitednatural_1543615404.jpg"/></ownedElement><opposite refid="af2a0bf8-3ea9-45e4-8a89-8810351edcc8" refElementId="af2a0bf8-3ea9-45e4-8a89-8810351edcc8" humanType="Property" classType="Property" name="base_Activity" icon="index_files/icon_property_1602862262.jpg" humanName="Opposite"/><namespace refid="addc852d-1847-4841-b9bd-0c6aacdf57ef" refElementId="addc852d-1847-4841-b9bd-0c6aacdf57ef" humanType="Extension" classType="Extension" name="Extension[extension_Sentinel Scenario:SentinelScenario - base_Activity:Activity]" isRelationship="true" icon="index_files/icon_extension_1763508892.jpg" humanName="Namespace"/><name humanName="Name">extension_Sentinel Scenario</name><multiplicity humanName="Multiplicity" mode="s,e">0..1</multiplicity><lowerValue refid="25a8354b-e241-4cf6-981d-62b159934ef4" refElementId="25a8354b-e241-4cf6-981d-62b159934ef4" humanType="Literal Integer" classType="LiteralInteger" name="0" text="0" icon="index_files/icon_literalinteger_602632507.jpg" humanName="Lower Value"/><lower humanName="Lower">0</lower><isUnique humanName="Is Unique">true</isUnique><isStatic humanName="Is Static">false</isStatic><isReadOnly humanName="Is Read Only">false</isReadOnly><isOrdered humanName="Is Ordered">false</isOrdered><isLeaf humanName="Is Leaf">false</isLeaf><isID humanName="Is ID" mode="s,e">false</isID><isDerivedUnion humanName="Is Derived Union">false</isDerivedUnion><isDerived humanName="Is Derived">false</isDerived><isComposite humanName="Is Composite">true</isComposite><featuringClassifier refid="addc852d-1847-4841-b9bd-0c6aacdf57ef" refElementId="addc852d-1847-4841-b9bd-0c6aacdf57ef" humanType="Extension" classType="Extension" name="Extension[extension_Sentinel Scenario:SentinelScenario - base_Activity:Activity]" isRelationship="true" icon="index_files/icon_extension_1763508892.jpg" humanName="Featuring Classifier"/><effectiveIRI humanName="Effective IRI"></effectiveIRI><documentation humanName="Documentation"></documentation><association refid="addc852d-1847-4841-b9bd-0c6aacdf57ef" refElementId="addc852d-1847-4841-b9bd-0c6aacdf57ef" humanType="Extension" classType="Extension" name="Extension[extension_Sentinel Scenario:SentinelScenario - base_Activity:Activity]" isRelationship="true" icon="index_files/icon_extension_1763508892.jpg" humanName="Association"/><aggregation humanName="Aggregation">composite</aggregation><TYPE_MODIFIER humanName="Type Modifier"></TYPE_MODIFIER><TO_DO humanName="To Do"></TO_DO><ActiveHyperlink humanName="Active Hyperlink"></ActiveHyperlink><ownedBy refid="addc852d-1847-4841-b9bd-0c6aacdf57ef" refElementId="addc852d-1847-4841-b9bd-0c6aacdf57ef" humanType="Extension" classType="Extension" name="Extension[extension_Sentinel Scenario:SentinelScenario - base_Activity:Activity]" isRelationship="true" icon="index_files/icon_extension_1763508892.jpg" humanName="Owned By" mode="s,e"/><navigable humanName="Navigable">true</navigable><report_appliedStereotype_tags humanName="Applied Stereotype" requireSort="element"/></extensionend></magicdraw>